STMutilities/__init__.py
STMutilities/goldstone/__init__.py
STMutilities/goldstone/ctranslation.py
STMutilities/goldstone/ivolume.py
povray/__init__.py
povray/cstmfromsource.py
povray/cvectorfromsource.py
povray/ipovfromsource.py
povray/energy_landscapes/__init__.py
povray/energy_landscapes/cenergylandscape.py
povray/energy_landscapes/pyvistascripts/__init__.py
povray/energy_landscapes/pyvistascripts/arrows.py
povray/energy_landscapes/pyvistascripts/energy_landscape1.py
povray/predefined_povrayobjects/__init__.py
povray/predefined_povrayobjects/ccamera.py
povray/predefined_povrayobjects/icamera.py
povray/utilities/__init__.py
povray/utilities/cfilterlattice.py
povray/utilities/colors.py
povray/utilities/spinconfiguration_utilities.py
povray/utilities/vaporyfurtherfeatures.py
povray/vapory_implementation/__init__.py
povray/vapory_scripts/__init__.py
povray/vapory_scripts/simple_cube.py
povray/vapory_scripts/spinconfigurations.py
results/__init__.py
results/igetresults.py
results/gneb/__init__.py
results/gneb/ccollect_sps.py
results/gneb/ccollect_succsesive_barr.py
results/gneb/cgn_opgneb.py
results/gneb/cgn_shortgneb.py
results/gneb/cgn_splitgneb.py
results/spindynamic/__init__.py
results/spindynamic/csd_skyrmion.py
shellcommands/__init__.py
shellcommands/constants.py
shellcommands/shellcommands.py
workscriputilities/__init__.py
workscriputilities/gneb/__init__.py
workscriputilities/gneb/functions.py
workscriputilities/gneb/succesive/__init__.py
workscriputilities/gneb/succesive/ccontinue_succsplit.py
workscriputilities/gneb/succesive/csuccsesive_onep.py
workscriputilities/gneb/succesive/csuccsesive_split.py
workscriputilities/gneb/succesive/isuccsesive.py
seafood_hs-0.1.60.dist-info/LICENSE
seafood_hs-0.1.60.dist-info/METADATA
seafood_hs-0.1.60.dist-info/WHEEL
seafood_hs-0.1.60.dist-info/top_level.txt
seafood_hs-0.1.60.dist-info/RECORD
