Metadata-Version: 2.1
Name: seafood-hs
Version: 0.1.60
Summary: Utilities for windows and linux
Home-page: https://gitlab.com/hschrautzer/seafood
Author: Hendrik Schrautzer
Author-email: h.schrautzer@gmx.de
License: UNKNOWN
Platform: UNKNOWN
Classifier: Programming Language :: Python :: 3
Classifier: License :: OSI Approved :: MIT License
Classifier: Operating System :: OS Independent
Requires-Python: >=3.6
